smaller_folders/__init__.py
smaller_folders/__main__.py
smaller_folders/cli.py
smaller_folders/core.py
smaller_folders/program_config.py
smaller_folders-0.1.2.dist-info/entry_points.txt
smaller_folders-0.1.2.dist-info/WHEEL
smaller_folders-0.1.2.dist-info/METADATA
smaller_folders-0.1.2.dist-info/RECORD
