Metadata-Version: 2.1
Name: smaller-folders
Version: 0.1.2
Summary: Split an arbitrary number of files into sub-folders containing a specified number of files each.
Home-page: https://github.com/aatifsyed/smaller_folders
License: MIT
Author: Aatif Syed
Author-email: aatif@aatifsyed.uk
Requires-Python: >=3.8,<4.0
Classifier: License :: OSI Approved :: MIT License
Classifier: Programming Language :: Python :: 3
Classifier: Programming Language :: Python :: 3.8
Classifier: Programming Language :: Python :: 3.9
Requires-Dist: more-itertools (>=8.6.0,<9.0.0)
Requires-Dist: natsort (>=7.1.0,<8.0.0)
Project-URL: Repository, https://github.com/aatifsyed/smaller_folders
